rtl/shift_unit.v
`timescale 1ns/1ps 

module shift_unit(
    //input 
    input [7:0]A,
    input shift_op, //can be change for phase 2

    //output 
    output reg [7:0]result,
    output reg shift_carry
);

always @(*) begin
    case(shift_op)
        //left shift
        1'b0 : begin 
                result[7] = A[6];
                result[6] = A[5];
                result[5] = A[4];
                result[4] = A[3];
                result[3] = A[2];
                result[2] = A[1];
                result[1] = A[0];
                result[0] = 1'b0;
                shift_carry = A[7];
        end 
        //Right shift 
        1'b1 : begin                
                //or we can simply write result      = A << 1;   
                //                       shift_carry = A[7];       
                result[7] = 1'b0;
                result[6] = A[7];
                result[5] = A[6];
                result[4] = A[5];
                result[3] = A[4];
                result[2] = A[3];
                result[1] = A[2];
                result[0] = A[1];
                shift_carry = A[0];
        end 
        //default condition 
        default : begin 
                    result = 8'b00000000;
                    shift_carry = 1'b0;
        end 

    endcase
end
endmodule

rtl/logical_unit.v
`timescale 1ns/1ps

module logical_unit(
    //input 
    input [7:0]A,
    input [7:0]B,
    input [1:0]opcode,

    //output
    output reg [7:0]result 
);

always @(*) begin 
    case(opcode)
        2'b00 : result = A & B;
        2'b01 : result = A | B;
        2'b10 : result = A ^ B;
        2'b11 : result = ~(A & B);
        default : result = 8'b00000000;
    endcase
end 
endmodule

rtl/half_adder.v
`timescale 1ns/1ps
module HA(
    input A,
    input B,
    output sum,
    output cout
);
    assign sum = A ^ B;
    assign cout = A & B;
endmodule

rtl/full_adder.v
`timescale 1ns/1ps

module FA(
    input A,
    input B,
    input cin,
    output sum,
    output cout
);

wire S1;
wire C1;
wire C2;

HA ha1 (
    .A(A),
    .B(B),
    .sum(S1),
    .cout(C1)
);

HA ha2(
    .A(S1),
    .B(cin),
    .sum(sum),
    .cout(C2)
);

or(cout , C1 , C2);

endmodule

rtl/ripple_adder_4bit.v
`timescale 1ns/1ps 

module RCA_4bit(
    input [3:0]A,
    input [3:0]B,
    input cin,
    output [3:0]sum,
    output cout,
    output carry_into_last_bit
);

wire c1;
wire c2;
wire c3;

FA FA1(
    .A(A[0]),
    .B(B[0]),
    .cin(cin),
    .sum(sum[0]),
    .cout(c1)
);

FA FA2(
    .A(A[1]),
    .B(B[1]),
    .cin(c1),
    .sum(sum[1]),
    .cout(c2)
);

FA FA3(
    .A(A[2]),
    .B(B[2]),
    .cin(c2),
    .sum(sum[2]),
    .cout(c3)
);

FA FA4(
    .A(A[3]),
    .B(B[3]),
    .cin(c3),
    .sum(sum[3]),
    .cout(cout)
);

assign carry_into_last_bit = c3;

endmodule

rtl/ripple_adder_8bit.v
`timescale 1ns/1ps

module RCA_8bit(
    input [7:0]A,
    input [7:0]B,
    input cin,
    output [7:0] sum,
    output cout,
    //for overflow 
    output carry_into_msb
);

// internal signal 
wire c1;

// 1st unit 
RCA_4bit u1_RCA_4bit(
    .A(A[3:0]),
    .B(B[3:0]),
    .cin(cin),
    .sum(sum[3:0]),
    .cout(c1)
);

//2nd unit 

RCA_4bit u2_RCA_4bit(
    .A(A[7:4]),
    .B(B[7:4]),
    .cin(c1),
    .sum(sum[7:4]),
    .cout(cout),
    .carry_into_last_bit(carry_into_msb)
);
endmodule

rtl/arithmetic_unit.v
`timescale 1ns/1ps

module arithmetic_unit(
    input [7:0]A,
    input [7:0]B,
    input sub,
    output [7:0]result,
    output cout,
    //for overflow
    output overflow
);

// internal wire 
wire [7:0]mod_b;
wire carry_into_msb;

// changing the value of B 
//5-3 = 5 +(-3) and -3 = 2's compliment of 3 
// sub = 0 = addition 
//sub = 1 = subtraction 
//{8{sub}} as sub is 1 bit data this is to convert 1 bit data to 8 bit data 

assign mod_b = B ^ {8{sub}};

//using RCA_8bit

RCA_8bit u1(
    .A(A),
    .B(mod_b),
    .cin(sub),
    .sum(result),
    .cout(cout),
    .carry_into_msb(carry_into_msb)  
);

assign overflow = cout ^ carry_into_msb; 

endmodule

rtl/alu.v
`timescale 1ns/1ps 

module alu(
    input [7:0]A,
    input [7:0]B,
    input [2:0]opcode,

    output reg [7:0]result,
    output reg carry_flag,
    output reg overflow_flag,
    output zero_flag,
    output negative_flag
);

//arithmatic unit  
wire [7:0]arithmetic_result;
wire arithmetic_cout;
wire arithmetic_overflow;
wire sub;

assign sub = (opcode == 3'b001);

//logical unit 
wire [7:0]logical_result;
reg [1:0]logical_op;

always @(*) begin
    case(opcode)
        3'b010 : logical_op = 2'b00; //AND 
        3'b011 : logical_op = 2'b01; //OR
        3'b100 : logical_op = 2'b10; //XOR
        3'b101 : logical_op = 2'b11; //NAND
        default : logical_op = 2'b00; 
    endcase
end 

//shift unit 
wire [7:0]shift_result;
wire shift_carry;
wire shift_op;

assign shift_op = opcode[0];

arithmetic_unit u1(
    .A(A),
    .B(B),
    .sub(sub),
    .result(arithmetic_result),
    .cout(arithmetic_cout),
    .overflow(arithmetic_overflow)
);

logical_unit u2(
    .A(A),
    .B(B),
    .opcode(logical_op),
    .result(logical_result)
);

shift_unit u3(
    .A(A),
    .shift_op(shift_op),
    .result(shift_result),
    .shift_carry(shift_carry)
);

always @(*) begin
    case(opcode)
        //ADD
        3'b000 : begin
            result = arithmetic_result;
            carry_flag = arithmetic_cout;
            overflow_flag = arithmetic_overflow;
        end 
        
        //SUB
        3'b001 : begin
            result = arithmetic_result;
            carry_flag = arithmetic_cout;
            overflow_flag = arithmetic_overflow;
        end

        //AND
        3'b010 : begin
            result = logical_result;
            carry_flag = 1'b0;
            overflow_flag = 1'b0;
        end

        //OR
        3'b011 : begin
            result = logical_result;
            carry_flag = 1'b0;
            overflow_flag = 1'b0;
        end

        //XOR
        3'b100 : begin
            result = logical_result;
            carry_flag = 1'b0;
            overflow_flag = 1'b0;
        end

        //NAND
        3'b101 : begin
            result = logical_result;
            carry_flag = 1'b0;
            overflow_flag = 1'b0;
        end

        //Left shift 
        3'b110 : begin
            result = shift_result;
            carry_flag = shift_carry;
            overflow_flag = 1'b0;
        end

        //Right shift 
        3'b111 : begin
            result = shift_result;
            carry_flag = shift_carry;
            overflow_flag = 1'b0;
        end

        //default case 
        default : begin
            result = 8'b00000000;
            carry_flag = 1'b0;
            overflow_flag = 1'b0;
        end
    endcase
end 

assign zero_flag = (result == 8'b00000000);
assign negative_flag = result[7];

endmodule

tb/alu_TB.v
`timescale 1ns/1ps

module alu_tb;

reg [7:0]A;
reg [7:0]B;
reg [2:0]opcode;

wire [7:0]result;
wire carry_flag;
wire overflow_flag;
wire negative_flag;
wire zero_flag;

alu dut(
    .A(A),
    .B(B),
    .opcode(opcode),
    .result(result),
    .carry_flag(carry_flag),
    .overflow_flag(overflow_flag),
    .negative_flag(negative_flag),
    .zero_flag(zero_flag)
);

initial begin
    $dumpfile("wave/alu.vcd");
    $dumpvars(0 , alu_tb);

    //case 1 : ADD 5 + 15 = 20 
    A = 8'b00000101;
    B = 8'b00001111;
    opcode = 3'b000;
    #10;

    // case 2 : ADD 127+1 =128 overflow = 1
    A = 8'b01111111;
    B = 8'b00000001;
    opcode = 3'b000;
    #10;

    //case 3 : SUB 15 - 10 = 5 
    A = 8'b00001111;
    B = 8'b00001010;
    opcode = 3'b001;
    #10;

    //case 4 : AND 
    A = 8'b00001111;
    B = 8'b00001010;
    opcode = 3'b010;
    #10;

    //case 5 : OR 
    A = 8'b00001111;
    B = 8'b00001010;
    opcode = 3'b011;
    #10;

    //case 6 : XOR 
    A = 8'b00001111;
    B = 8'b00001010;
    opcode = 3'b100;
    #10;

    //case 7 : NAND
    A = 8'b00001111;
    B = 8'b00001010;
    opcode = 3'b101;
    #10;

    //case 8 : Left shift  
    A = 8'b00001111;
    opcode = 3'b110;
    #10;

    //case 9 : Right shift  
    A = 8'b00001111;
    opcode = 3'b111;
    #10;

    $finish;
end 
endmodule

wave/alu.vcd
$date
	Tue Jul 28 14:46:27 2026
$end
$version
	Icarus Verilog
$end
$timescale
	1ps
$end
$scope module alu_tb $end
$var wire 1 ! zero_flag $end
$var wire 8 " result [7:0] $end
$var wire 1 # overflow_flag $end
$var wire 1 $ negative_flag $end
$var wire 1 % carry_flag $end
$var reg 8 & A [7:0] $end
$var reg 8 ' B [7:0] $end
$var reg 3 ( opcode [2:0] $end
$scope module dut $end
$var wire 8 ) A [7:0] $end
$var wire 8 * B [7:0] $end
$var wire 3 + opcode [2:0] $end
$var wire 1 ! zero_flag $end
$var wire 1 , sub $end
$var wire 8 - shift_result [7:0] $end
$var wire 1 . shift_op $end
$var wire 1 / shift_carry $end
$var wire 1 $ negative_flag $end
$var wire 8 0 logical_result [7:0] $end
$var wire 8 1 arithmetic_result [7:0] $end
$var wire 1 2 arithmetic_overflow $end
$var wire 1 3 arithmetic_cout $end
$var reg 1 % carry_flag $end
$var reg 2 4 logical_op [1:0] $end
$var reg 1 # overflow_flag $end
$var reg 8 5 result [7:0] $end
$scope module u1 $end
$var wire 8 6 A [7:0] $end
$var wire 8 7 B [7:0] $end
$var wire 8 8 mod_b [7:0] $end
$var wire 1 2 overflow $end
$var wire 1 , sub $end
$var wire 8 9 result [7:0] $end
$var wire 1 3 cout $end
$var wire 1 : carry_into_msb $end
$scope module u1 $end
$var wire 8 ; A [7:0] $end
$var wire 8 < B [7:0] $end
$var wire 1 , cin $end
$var wire 8 = sum [7:0] $end
$var wire 1 3 cout $end
$var wire 1 : carry_into_msb $end
$var wire 1 > c1 $end
$scope module u1_RCA_4bit $end
$var wire 4 ? A [3:0] $end
$var wire 4 @ B [3:0] $end
$var wire 1 A carry_into_last_bit $end
$var wire 1 , cin $end
$var wire 4 B sum [3:0] $end
$var wire 1 > cout $end
$var wire 1 C c3 $end
$var wire 1 D c2 $end
$var wire 1 E c1 $end
$scope module FA1 $end
$var wire 1 F A $end
$var wire 1 G B $end
$var wire 1 , cin $end
$var wire 1 E cout $end
$var wire 1 H sum $end
$var wire 1 I S1 $end
$var wire 1 J C2 $end
$var wire 1 K C1 $end
$scope module ha1 $end
$var wire 1 F A $end
$var wire 1 G B $end
$var wire 1 K cout $end
$var wire 1 I sum $end
$upscope $end
$scope module ha2 $end
$var wire 1 I A $end
$var wire 1 , B $end
$var wire 1 J cout $end
$var wire 1 H sum $end
$upscope $end
$upscope $end
$scope module FA2 $end
$var wire 1 L A $end
$var wire 1 M B $end
$var wire 1 E cin $end
$var wire 1 D cout $end
$var wire 1 N sum $end
$var wire 1 O S1 $end
$var wire 1 P C2 $end
$var wire 1 Q C1 $end
$scope module ha1 $end
$var wire 1 L A $end
$var wire 1 M B $end
$var wire 1 Q cout $end
$var wire 1 O sum $end
$upscope $end
$scope module ha2 $end
$var wire 1 O A $end
$var wire 1 E B $end
$var wire 1 P cout $end
$var wire 1 N sum $end
$upscope $end
$upscope $end
$scope module FA3 $end
$var wire 1 R A $end
$var wire 1 S B $end
$var wire 1 D cin $end
$var wire 1 C cout $end
$var wire 1 T sum $end
$var wire 1 U S1 $end
$var wire 1 V C2 $end
$var wire 1 W C1 $end
$scope module ha1 $end
$var wire 1 R A $end
$var wire 1 S B $end
$var wire 1 W cout $end
$var wire 1 U sum $end
$upscope $end
$scope module ha2 $end
$var wire 1 U A $end
$var wire 1 D B $end
$var wire 1 V cout $end
$var wire 1 T sum $end
$upscope $end
$upscope $end
$scope module FA4 $end
$var wire 1 X A $end
$var wire 1 Y B $end
$var wire 1 C cin $end
$var wire 1 > cout $end
$var wire 1 Z sum $end
$var wire 1 [ S1 $end
$var wire 1 \ C2 $end
$var wire 1 ] C1 $end
$scope module ha1 $end
$var wire 1 X A $end
$var wire 1 Y B $end
$var wire 1 ] cout $end
$var wire 1 [ sum $end
$upscope $end
$scope module ha2 $end
$var wire 1 [ A $end
$var wire 1 C B $end
$var wire 1 \ cout $end
$var wire 1 Z sum $end
$upscope $end
$upscope $end
$upscope $end
$scope module u2_RCA_4bit $end
$var wire 4 ^ A [3:0] $end
$var wire 4 _ B [3:0] $end
$var wire 1 : carry_into_last_bit $end
$var wire 1 > cin $end
$var wire 4 ` sum [3:0] $end
$var wire 1 3 cout $end
$var wire 1 a c3 $end
$var wire 1 b c2 $end
$var wire 1 c c1 $end
$scope module FA1 $end
$var wire 1 d A $end
$var wire 1 e B $end
$var wire 1 > cin $end
$var wire 1 c cout $end
$var wire 1 f sum $end
$var wire 1 g S1 $end
$var wire 1 h C2 $end
$var wire 1 i C1 $end
$scope module ha1 $end
$var wire 1 d A $end
$var wire 1 e B $end
$var wire 1 i cout $end
$var wire 1 g sum $end
$upscope $end
$scope module ha2 $end
$var wire 1 g A $end
$var wire 1 > B $end
$var wire 1 h cout $end
$var wire 1 f sum $end
$upscope $end
$upscope $end
$scope module FA2 $end
$var wire 1 j A $end
$var wire 1 k B $end
$var wire 1 c cin $end
$var wire 1 b cout $end
$var wire 1 l sum $end
$var wire 1 m S1 $end
$var wire 1 n C2 $end
$var wire 1 o C1 $end
$scope module ha1 $end
$var wire 1 j A $end
$var wire 1 k B $end
$var wire 1 o cout $end
$var wire 1 m sum $end
$upscope $end
$scope module ha2 $end
$var wire 1 m A $end
$var wire 1 c B $end
$var wire 1 n cout $end
$var wire 1 l sum $end
$upscope $end
$upscope $end
$scope module FA3 $end
$var wire 1 p A $end
$var wire 1 q B $end
$var wire 1 b cin $end
$var wire 1 a cout $end
$var wire 1 r sum $end
$var wire 1 s S1 $end
$var wire 1 t C2 $end
$var wire 1 u C1 $end
$scope module ha1 $end
$var wire 1 p A $end
$var wire 1 q B $end
$var wire 1 u cout $end
$var wire 1 s sum $end
$upscope $end
$scope module ha2 $end
$var wire 1 s A $end
$var wire 1 b B $end
$var wire 1 t cout $end
$var wire 1 r sum $end
$upscope $end
$upscope $end
$scope module FA4 $end
$var wire 1 v A $end
$var wire 1 w B $end
$var wire 1 a cin $end
$var wire 1 3 cout $end
$var wire 1 x sum $end
$var wire 1 y S1 $end
$var wire 1 z C2 $end
$var wire 1 { C1 $end
$scope module ha1 $end
$var wire 1 v A $end
$var wire 1 w B $end
$var wire 1 { cout $end
$var wire 1 y sum $end
$upscope $end
$scope module ha2 $end
$var wire 1 y A $end
$var wire 1 a B $end
$var wire 1 z cout $end
$var wire 1 x sum $end
$upscope $end
$upscope $end
$upscope $end
$upscope $end
$upscope $end
$scope module u2 $end
$var wire 8 | A [7:0] $end
$var wire 8 } B [7:0] $end
$var wire 2 ~ opcode [1:0] $end
$var reg 8 !" result [7:0] $end
$upscope $end
$scope module u3 $end
$var wire 8 "" A [7:0] $end
$var wire 1 . shift_op $end
$var reg 8 #" result [7:0] $end
$var reg 1 / shift_carry $end
$upscope $end
$upscope $end
$upscope $end
$enddefinitions $end
$comment Show the parameter values. $end
$dumpall
$end
#0
$dumpvars
b1010 #"
b101 ""
b101 !"
b0 ~
b1111 }
b101 |
0{
0z
0y
0x
0w
0v
0u
0t
0s
0r
0q
0p
0o
0n
0m
0l
0k
0j
0i
0h
0g
1f
0e
0d
0c
0b
0a
b1 `
b0 _
b0 ^
0]
1\
1[
0Z
1Y
0X
1W
0V
0U
1T
1S
1R
0Q
1P
1O
0N
1M
0L
1K
0J
0I
0H
1G
1F
1E
1D
1C
b100 B
1A
b1111 @
b101 ?
1>
b10100 =
b1111 <
b101 ;
0:
b10100 9
b1111 8
b1111 7
b101 6
b10100 5
b0 4
03
02
b10100 1
b101 0
0/
0.
b1010 -
0,
b0 +
b1111 *
b101 )
b0 (
b1111 '
b101 &
0%
0$
0#
b10100 "
0!
$end
#10000
0!
1$
1#
1x
12
1:
1a
1t
0T
1V
1b
1n
1A
1C
1D
1>
1c
b10000000 "
b10000000 5
1U
0W
0N
1P
b0 B
0Z
1\
0f
1h
0l
b10000000 1
b10000000 9
b10000000 =
b1000 `
0r
0M
0S
0Y
1O
0Q
1[
0]
1g
1m
1s
b1 @
1L
1X
1d
1j
1p
b1 8
b1 <
b1111 ?
b111 ^
b1 0
b1 !"
b11111110 -
b11111110 #"
b1 '
b1 *
b1 7
b1 }
b1111111 &
b1111111 )
b1111111 6
b1111111 ;
b1111111 |
b1111111 ""
#20000
1%
0$
13
0x
1z
0#
02
1T
0V
1c
1b
1:
1a
0U
1W
1y
0f
1h
0l
1n
b0 `
0r
1t
1S
1e
1k
1q
1w
1g
1m
1s
1/
b101 @
b1111 _
0d
0j
0p
b101 "
b101 5
b101 1
b101 9
b101 =
b101 B
1H
1.
b11110101 8
b11110101 <
b0 ^
b1010 0
b1010 !"
b111 -
b111 #"
1,
b1 (
b1 +
b1010 '
b1010 *
b1010 7
b1010 }
b1111 &
b1111 )
b1111 6
b1111 ;
b1111 |
b1111 ""
#30000
0c
0b
0:
0a
03
0E
0N
0P
0T
1V
1A
1C
1Z
0\
1f
0h
0l
0n
0r
0t
b1 `
0x
0z
1I
0K
0O
1Q
1U
0W
0[
1]
0g
0m
0s
0y
0G
1M
0S
1Y
0e
0k
0q
0w
b1010 @
b0 _
0/
b11110 -
b11110 #"
0%
b1010 "
b1010 5
b1010 8
b1010 <
b11001 1
b11001 9
b11001 =
b1001 B
1H
0.
0,
b10 (
b10 +
#40000
b1111 "
b1111 5
b1111 0
b1111 !"
1/
b111 -
b111 #"
b1 4
b1 ~
1.
b11 (
b11 +
#50000
b101 "
b101 5
b101 0
b101 !"
0/
b11110 -
b11110 #"
b10 4
b10 ~
0.
b100 (
b100 +
#60000
1$
b11110101 "
b11110101 5
b11110101 0
b11110101 !"
1/
b111 -
b111 #"
b11 4
b11 ~
1.
b101 (
b101 +
#70000
0$
b1010 0
b1010 !"
0/
b11110 -
b11110 #"
0%
b11110 "
b11110 5
b0 4
b0 ~
0.
b110 (
b110 +
#80000
1%
b111 "
b111 5
1/
b111 -
b111 #"
1.
b111 (
b111 +
