rtl/half_adder.v
`timescale 1ns/1ps
module HA(
    input A,
    input B,
    output sum,
    output cout
);
    assign sum = A ^ B;
    assign cout = A & B;
endmodule

rtl/full_adder.v
`timescale 1ns/1ps

module FA(
    input A,
    input B,
    input cin,
    output sum,
    output cout
);

wire S1;
wire C1;
wire C2;

HA ha1 (
    .A(A),
    .B(B),
    .sum(S1),
    .cout(C1)
);

HA ha2(
    .A(S1),
    .B(cin),
    .sum(sum),
    .cout(C2)
);

or(cout , C1 , C2);

endmodule

tb/full_adder_TB.v
`timescale 1ns/1ps

module FA_TB;
reg A;
reg B;
reg cin;
wire sum;
wire cout;

FA dut(
    .A(A),
    .B(B),
    .cin(cin),
    .sum(sum),
    .cout(cout)
);

initial begin

    $dumpfile("wave/Full_adder.vcd");
    $dumpvars(0,FA_TB);

    A = 0 ; B = 0 ; cin = 0 ;
    #10;
    A = 0 ; B = 0 ; cin = 1 ;
    #10;
    A = 0 ; B = 1 ; cin = 0 ;
    #10;
    A = 0 ; B = 1 ; cin = 1 ;
    #10;
    A = 1 ; B = 0 ; cin = 0 ;
    #10;
    A = 1 ; B = 0 ; cin = 1 ;
    #10;
    A = 1 ; B = 1 ; cin = 0 ;
    #10;
    A = 1 ; B = 1 ; cin = 1 ;
    #10;
    $finish;
end 

endmodule

wave/Full_adder.vcd
$date
	Fri Jul 24 21:51:16 2026
$end
$version
	Icarus Verilog
$end
$timescale
	1ps
$end
$scope module FA_TB $end
$var wire 1 ! sum $end
$var wire 1 " cout $end
$var reg 1 # A $end
$var reg 1 $ B $end
$var reg 1 % cin $end
$scope module dut $end
$var wire 1 # A $end
$var wire 1 $ B $end
$var wire 1 " cout $end
$var wire 1 % cin $end
$var wire 1 ! sum $end
$var wire 1 & S1 $end
$var wire 1 ' C2 $end
$var wire 1 ( C1 $end
$scope module ha1 $end
$var wire 1 # A $end
$var wire 1 $ B $end
$var wire 1 ( cout $end
$var wire 1 & sum $end
$upscope $end
$scope module ha2 $end
$var wire 1 & A $end
$var wire 1 % B $end
$var wire 1 ' cout $end
$var wire 1 ! sum $end
$upscope $end
$upscope $end
$upscope $end
$enddefinitions $end
$comment Show the parameter values. $end
$dumpall
$end
#0
$dumpvars
0(
0'
0&
0%
0$
0#
0"
0!
$end
#10000
1!
1%
#20000
1&
0%
1$
#30000
1"
0!
1'
1%
#40000
0"
1!
0'
0%
0$
1#
#50000
1"
0!
1'
1%
#60000
0'
0&
1(
0%
1$
#70000
1!
1%
